MANIFEST.in
README.rst
setup.py
Elasticsearch_Raven.egg-info/PKG-INFO
Elasticsearch_Raven.egg-info/SOURCES.txt
Elasticsearch_Raven.egg-info/dependency_links.txt
Elasticsearch_Raven.egg-info/requires.txt
Elasticsearch_Raven.egg-info/top_level.txt
bin/amqp_to_elasticsearch.py
bin/elasticsearch-raven.py
bin/udp_to_amqp.py
bin/update_ids.py
elasticsearch_raven/__init__.py
elasticsearch_raven/amqp.py
elasticsearch_raven/exceptions.py
elasticsearch_raven/http.py
elasticsearch_raven/postfix.py
elasticsearch_raven/queue_sender.py
elasticsearch_raven/queues.py
elasticsearch_raven/transport.py
elasticsearch_raven/udp_handler.py
elasticsearch_raven/udp_server.py
elasticsearch_raven/utils.py
elasticsearch_raven/wsgi.py