Metadata-Version: 1.0
Name: Elasticsearch-Raven
Version: 1.5.0
Summary: Proxy that allows to send logs from Raven to Elasticsearch.
Home-page: https://github.com/pozytywnie/elasticsearch-raven/
Author: Tomasz Wysocki
Author-email: tomasz@pozytywnie.pl
License: MIT
Platform: UNKNOWN
